{
  "pages": [
    {
      "path": "pages/home/index",
      "style": {
        "navigationBarTitleText": "首页"
      }
    },
    {
      "path": "pages/login/index",
      "style": {
        "navigationBarTitleText": "登录"
      }
    },
    {
      "path": "pages/me/index",
      "style": {
        "navigationBarTitleText": "我的"
      }
    }
  ],
  "globalStyle": {
    "navigationBarBackgroundColor": "#3C9AFC",
    "navigationBarTextStyle": "white"
  },
  "tabBar": {
    "color": "#bfbfbf",
    "selectedColor": "#1296db",
    "borderStyle": "black",
    "backgroundColor": "#ffffff",
    "list": [
      {
        "pagePath": "pages/home/index",
        "text": "首页",
        "iconPath": "static/images/home1.png",
        "selectedIconPath": "static/images/home2.png"
      },
      {
        "pagePath": "pages/me/index",
        "text": "我的",
        "iconPath": "static/images/charts1.png",
        "selectedIconPath": "static/images/charts2.png"
      }
    ]
  }
}